flask_ultime/__init__.py
flask_ultime/cli.py
flask_ultime/constants.py
flask_ultime/ultime.py
flask_ultime/utils.py
flask_ultime-0.1.0.dist-info/LICENSE
flask_ultime-0.1.0.dist-info/METADATA
flask_ultime-0.1.0.dist-info/WHEEL
flask_ultime-0.1.0.dist-info/top_level.txt
flask_ultime-0.1.0.dist-info/RECORD
