Metadata-Version: 2.2
Name: flask_ultime
Version: 0.1.0
Summary: A Flask extension to integrate TailwindCSS and Alpine.js.
Home-page: https://github.com/codewithmpia/flask_ultime
Author: codewithmpia
Author-email: codewithmpia@gmail.com
Classifier: Development Status :: 4 - Beta
Classifier: Intended Audience :: Developers
Classifier: License :: OSI Approved :: MIT License
Classifier: Programming Language :: Python :: 3
Classifier: Programming Language :: Python :: 3.6
Classifier: Programming Language :: Python :: 3.7
Classifier: Programming Language :: Python :: 3.8
Classifier: Programming Language :: Python :: 3.9
Classifier: Framework :: Flask
Requires-Python: >=3.6
License-File: LICENSE
Requires-Dist: Flask
Requires-Dist: requests
Dynamic: author
Dynamic: author-email
Dynamic: classifier
Dynamic: description
Dynamic: description-content-type
Dynamic: home-page
Dynamic: requires-dist
Dynamic: requires-python
Dynamic: summary
